MANIFEST.in
setup.py
scaffold/__init__.py
scaffold/scaffold.py
scaffold/templates.tar.gz
scaffold/utils/__init__.py
scaffold/utils/command_parser.py
scaffold/utils/config_parser.py
scaffold/utils/exceptions.py
scaffold/utils/handler.py
scaffold/utils/template.py
scaffolding.egg-info/PKG-INFO
scaffolding.egg-info/SOURCES.txt
scaffolding.egg-info/dependency_links.txt
scaffolding.egg-info/entry_points.txt
scaffolding.egg-info/not-zip-safe
scaffolding.egg-info/requires.txt
scaffolding.egg-info/top_level.txt