Metadata-Version: 1.0
Name: scaffolding
Version: 0.2.0
Summary: Setup your project layout by templates
Home-page: https://github.com/MinweiShen/scaffolding
Author: Minwei Shen
Author-email: minweishen1991@gmail.com
License: UNKNOWN
Platform: UNKNOWN
